dsdiagram/__init__.py
dsdiagram/dsdiagram.py
dsdiagram-0.0.3.dist-info/LICENSE
dsdiagram-0.0.3.dist-info/METADATA
dsdiagram-0.0.3.dist-info/WHEEL
dsdiagram-0.0.3.dist-info/top_level.txt
dsdiagram-0.0.3.dist-info/RECORD
