Metadata-Version: 2.1
Name: dsdiagram
Version: 0.0.3
Summary: data structure diagram generator
Author: David Chen
Project-URL: Homepage, https://github.com/David0922/gen-data-structure-diagram
Requires-Python: >=3.11
License-File: LICENSE
Requires-Dist: graphviz
